rag_evaluator/__init__.py
rag_evaluator/evaluator.py
rag_evaluator/test_evaluator.py
rag_evaluator-0.1.0.dist-info/METADATA
rag_evaluator-0.1.0.dist-info/WHEEL
rag_evaluator-0.1.0.dist-info/top_level.txt
rag_evaluator-0.1.0.dist-info/RECORD
